{
    "Personajes": [
        {
            "Stats": {
                "raza": "HUMANO",
                "agilidad": 16,
                "experiencia": 0,
                "nombre": "a",
                "fuerza": 51,
                "constitucion": 77,
                "nivel": 1,
                "vidaMax": 127
            },
            "Equipamientos": {
                "Armadura": {
                    "Casco": {},
                    "Pechera": {
                        "nombre": "Pechera de madera",
                        "rareza": "RARE",
                        "nivel": 1,
                        "xp": 0
                    },
                    "Pantalon": {
                        "nombre": "Pantalón de madera",
                        "rareza": "RARE",
                        "nivel": 1,
                        "xp": 0
                    },
                    "Botas": {}
                },
                "Arma": [
                    {
                        "nombre": "Espada de Madera",
                        "rareza": "COMMUN",
                        "nivel": 1,
                        "xp": 0,
                        "afinidad": "CORTE"
                    }
                ]
            }
        },
        {
            "Stats": {
                "raza": "HUMANO",
                "agilidad": 16,
                "experiencia": 0,
                "nombre": "b",
                "fuerza": 51,
                "constitucion": 77,
                "nivel": 1,
                "vidaMax": 127
            },
            "Equipamientos": {
                "Armadura": {
                    "Casco": {},
                    "Pechera": {
                        "nombre": "Pechera de madera",
                        "rareza": "RARE",
                        "nivel": 1,
                        "xp": 0
                    },
                    "Pantalon": {
                        "nombre": "Pantalón de madera",
                        "rareza": "RARE",
                        "nivel": 1,
                        "xp": 0
                    },
                    "Botas": {}
                },
                "Arma": [
                    {
                        "nombre": "Espada de Madera",
                        "rareza": "COMMUN",
                        "nivel": 1,
                        "xp": 0,
                        "afinidad": "CORTE"
                    }
                ]
            }
        }
    ]
}